uwg/BEMDef.py
uwg/RSMDef.py
uwg/UBLDef.py
uwg/UCMDef.py
uwg/__init__.py
uwg/__main__.py
uwg/building.py
uwg/element.py
uwg/forcing.py
uwg/infracalcs.py
uwg/material.py
uwg/param.py
uwg/psychrometrics.py
uwg/readDOE.py
uwg/schdef.py
uwg/simparam.py
uwg/solarcalcs.py
uwg/urbflux.py
uwg/utilities.py
uwg/uwg.py
uwg/weather.py
uwg/cli/__init__.py
uwg/cli/simulate.py
uwg/cli/validate.py
uwg/refdata/readDOE.pkl
uwg/refdata/z_meso.txt
uwg-5.8.13.dist-info/LICENSE
uwg-5.8.13.dist-info/METADATA
uwg-5.8.13.dist-info/WHEEL
uwg-5.8.13.dist-info/entry_points.txt
uwg-5.8.13.dist-info/top_level.txt
uwg-5.8.13.dist-info/RECORD
