Metadata-Version: 2.1
Name: uwg
Version: 5.8.13
Summary: Python application for modeling the urban heat island effect.
Home-page: https://github.com/ladybug-tools/uwg
Author: Ladybug Tools
Author-email: info@ladybug.tools
Classifier: Programming Language :: Python :: 2.7
Classifier: Programming Language :: Python :: 3.6
Classifier: Programming Language :: Python :: 3.7
Classifier: Programming Language :: Python :: Implementation :: CPython
Classifier: License :: OSI Approved :: GNU General Public License v3 (GPLv3)
Classifier: Operating System :: OS Independent
Provides-Extra: cli
License-File: LICENSE
